SATO/SATO.py
SATO/__init__.py
SATO/about_intro.txt
SATO/help.txt
SATO/stylesheet.css
SATO/validation.py
SATO/icons/download.png
SATO/icons/fasta.png
SATO/icons/file.png
SATO/icons/logo-no-background.png
SATO/icons/sato.png
SATO-0.1.7.data/scripts/run.py
SATO-0.1.7.dist-info/LICENSE
SATO-0.1.7.dist-info/METADATA
SATO-0.1.7.dist-info/WHEEL
SATO-0.1.7.dist-info/entry_points.txt
SATO-0.1.7.dist-info/top_level.txt
SATO-0.1.7.dist-info/RECORD
