Metadata-Version: 2.1
Name: SATO
Version: 0.1.7
Summary: Python package that generates consensus sequence from the forward and reverse sequences, performs multiple sequence alignment of the fasta sequences, and generates phylogenetic trees using Bayesian and Maximum Likelihood Methods
Home-page: https://github.com/clabe-wekesa/SATO
Author: Clabe Wekesa
Author-email: simiyu86wekesa@gmail.com
License: MIT
Keywords: consensus,alignment,phylogenetics,bioinformatics
Classifier: License :: OSI Approved :: MIT License
Classifier: Development Status :: 3 - Alpha
Classifier: Intended Audience :: Science/Research
Classifier: Programming Language :: Python :: 3
Classifier: Programming Language :: Python :: 3.6
Classifier: Programming Language :: Python :: 3.7
Classifier: Programming Language :: Python :: 3.8
Classifier: Programming Language :: Python :: 3.9
Classifier: Programming Language :: Python :: 3.10
Classifier: Programming Language :: Python :: 3.11
Classifier: Operating System :: OS Independent
Requires-Python: >=3.6
License-File: LICENSE
Requires-Dist: PyQt6
Requires-Dist: Biopython
